{
  "best_score": 0.8143682513871887,
  "best_params": {
    "sgd__alpha": 0.01
  },
  "candidates": [
    {
      "sgd__alpha": 0.1
    },
    {
      "sgd__alpha": 50.0
    },
    {
      "sgd__alpha": 0.05
    },
    {
      "sgd__alpha": 0.01
    },
    {
      "sgd__alpha": 100.0
    },
    {
      "sgd__alpha": 10.0
    },
    {
      "sgd__alpha": 0.005
    },
    {
      "sgd__alpha": 0.0001
    },
    {
      "sgd__alpha": 0.5
    },
    {
      "sgd__alpha": 0.0005
    },
    {
      "sgd__alpha": 0.001
    },
    {
      "sgd__alpha": 5.0
    },
    {
      "sgd__alpha": 1e-06
    },
    {
      "sgd__alpha": 1e-05
    },
    {
      "sgd__alpha": 1.0
    }
  ],
  "evaluated": [
    {
      "params": {
        "sgd__alpha": 0.1
      },
      "score": 0.8136592261053714
    },
    {
      "params": {
        "sgd__alpha": 50.0
      },
      "score": 0.23182502970101945
    },
    {
      "params": {
        "sgd__alpha": 0.05
      },
      "score": 0.8140268158807862
    },
    {
      "params": {
        "sgd__alpha": 0.01
      },
      "score": 0.8143682513871887
    },
    {
      "params": {
        "sgd__alpha": 100.0
      },
      "score": 0.23021810602332451
    },
    {
      "params": {
        "sgd__alpha": 10.0
      },
      "score": 0.7866861913801376
    },
    {
      "params": {
        "sgd__alpha": 0.005
      },
      "score": 0.8138738130251081
    },
    {
      "params": {
        "sgd__alpha": 0.0001
      },
      "score": 0.775930286986657
    },
    {
      "params": {
        "sgd__alpha": 0.5
      },
      "score": 0.8107264655802535
    },
    {
      "params": {
        "sgd__alpha": 0.0005
      },
      "score": 0.8076418200557081
    },
    {
      "params": {
        "sgd__alpha": 0.001
      },
      "score": 0.812703035459213
    },
    {
      "params": {
        "sgd__alpha": 5.0
      },
      "score": 0.7914047730020415
    },
    {
      "params": {
        "sgd__alpha": 1e-06
      },
      "score": 0.7542512548961178
    },
    {
      "params": {
        "sgd__alpha": 1e-05
      },
      "score": 0.7599986400826959
    },
    {
      "params": {
        "sgd__alpha": 1.0
      },
      "score": 0.8074368880949855
    }
  ]
}